pybuilder_pytest_coverage/__init__.py
pybuilder_pytest_coverage-1.1.2.dist-info/DESCRIPTION.rst
pybuilder_pytest_coverage-1.1.2.dist-info/METADATA
pybuilder_pytest_coverage-1.1.2.dist-info/RECORD
pybuilder_pytest_coverage-1.1.2.dist-info/WHEEL
pybuilder_pytest_coverage-1.1.2.dist-info/metadata.json
pybuilder_pytest_coverage-1.1.2.dist-info/namespace_packages.txt
pybuilder_pytest_coverage-1.1.2.dist-info/top_level.txt
pybuilder_pytest_coverage-1.1.2.dist-info/zip-safe
